epd1in54/__init__.py
epd1in54/__main__.py
epd1in54/epdif.py
epd1in54b/__init__.py
epd1in54b/__main__.py
epd1in54b/epdif.py
epd1in54b/imagedata.py
epd1in54c/__init__.py
epd1in54c/__main__.py
epd1in54c/epdif.py
epd2in13/__init__.py
epd2in13/__main__.py
epd2in13/epdif.py
epd2in13b/__init__.py
epd2in13b/__main__.py
epd2in13b/epdif.py
epd2in7/__init__.py
epd2in7/__main__.py
epd2in7/epdif.py
epd2in7b/__init__.py
epd2in7b/__main__.py
epd2in7b/epdif.py
epd2in9/__init__.py
epd2in9/__main__.py
epd2in9/epdif.py
epd2in9b/__init__.py
epd2in9b/__main__.py
epd2in9b/epdif.py
epd4in2/__init__.py
epd4in2/__main__.py
epd4in2/epdif.py
epd4in2b/__init__.py
epd4in2b/__main__.py
epd4in2b/epdif.py
epd7in5/__init__.py
epd7in5/__main__.py
epd7in5/epdif.py
epd7in5b/__init__.py
epd7in5b/__main__.py
epd7in5b/epdif.py
epd_library-0.2.3.dist-info/LICENSE
epd_library-0.2.3.dist-info/METADATA
epd_library-0.2.3.dist-info/WHEEL
epd_library-0.2.3.dist-info/entry_points.txt
epd_library-0.2.3.dist-info/top_level.txt
epd_library-0.2.3.dist-info/RECORD
