Metadata-Version: 2.1
Name: epd-library
Version: 0.2.3
Summary: e-paper for raspberry pi (Waveshare e-paper)
Home-page: https://github.com/t4skforce/epd-library
Author: t4skforce
Author-email: 7422037+t4skforce@users.noreply.github.com
License: UNKNOWN
Platform: UNKNOWN
Classifier: Environment :: Console
Classifier: Programming Language :: Python :: 2.7
Classifier: Programming Language :: Python :: 3.5
Classifier: Programming Language :: Python :: 3.6
Classifier: Programming Language :: Python :: 3.7
Classifier: Programming Language :: Python :: 3.8
Classifier: Natural Language :: English
Classifier: License :: OSI Approved :: GNU General Public License v3 (GPLv3)
Classifier: Operating System :: POSIX :: Linux
Requires-Python: >=2.7, !=3.0.*, !=3.1.*, !=3.2.*, !=3.3.*, <4
